LICENSE
MANIFEST.in
README.rst
runtests.py
setup.py
django_gearman_commands/__init__.py
django_gearman_commands/models.py
django_gearman_commands/settings.py
django_gearman_commands.egg-info/PKG-INFO
django_gearman_commands.egg-info/SOURCES.txt
django_gearman_commands.egg-info/dependency_links.txt
django_gearman_commands.egg-info/requires.txt
django_gearman_commands.egg-info/top_level.txt
django_gearman_commands/management/__init__.py
django_gearman_commands/management/commands/__init__.py
django_gearman_commands/management/commands/gearman_server_info.py
django_gearman_commands/management/commands/gearman_submit_job.py
django_gearman_commands/management/commands/gearman_worker_footest.py
django_gearman_commands/tests/__init__.py
django_gearman_commands/tests/test_django_gearman_commands.py