Metadata-Version: 1.1
Name: django-gearman-commands
Version: 0.6.0
Summary: Django management commands for working with Gearman job server from Django framework
Home-page: http://www.codescale.net/en/community#django-gearman-commands
Author: Jozef Ševčík
Author-email: info@codescale.net
License: BSD
Download-URL: http://github.com/CodeScaleInc/django-gearman-commands/tarball/master
Keywords: django gearman gearmand jobs queue
Platform: any
Classifier: Development Status :: 5 - Production/Stable
Classifier: Environment :: Console
Classifier: Environment :: Web Environment
Classifier: Intended Audience :: Developers
Classifier: Intended Audience :: System Administrators
Classifier: License :: OSI Approved :: BSD License
Classifier: Operating System :: OS Independent
Classifier: Programming Language :: Python
Classifier: Topic :: Utilities
Classifier: Framework :: Django
